oura/__init__.py
oura/auth.py
oura/client.py
oura/client_pandas.py
oura/converters.py
oura/exceptions.py
oura/export/__init__.py
oura/export/writers.py
oura/v2/__init__.py
oura/v2/client.py
oura/v2/client_pandas.py
oura-1.3.0.dist-info/LICENSE
oura-1.3.0.dist-info/METADATA
oura-1.3.0.dist-info/WHEEL
oura-1.3.0.dist-info/top_level.txt
oura-1.3.0.dist-info/RECORD
