Metadata-Version: 2.1
Name: oura
Version: 1.3.0
Summary: Oura API client
Home-page: https://github.com/turing-complet/python-ouraring
Author: turing-complet
Author-email: turingcomplet@proton.me
Project-URL: Bug Tracker, https://github.com/turing-complet/python-ouraring/issues
Classifier: License :: OSI Approved :: MIT License
Classifier: Operating System :: OS Independent
Classifier: Programming Language :: Python :: 3
Classifier: Programming Language :: Python :: 3.8
Classifier: Programming Language :: Python :: 3.9
Requires-Python: >=3.8
License-File: LICENSE
Requires-Dist: requests-oauthlib
Requires-Dist: pandas
